typeddict_validator/__init__.py
typeddict_validator/validate.py
typeddict_validator/validate_test.py
typeddict_validator-0.2.0.dist-info/licenses/LICENSE
typeddict_validator-0.2.0.dist-info/METADATA
typeddict_validator-0.2.0.dist-info/WHEEL
typeddict_validator-0.2.0.dist-info/top_level.txt
typeddict_validator-0.2.0.dist-info/RECORD
