Metadata-Version: 2.4
Name: typeddict-validator
Version: 0.2.0
Classifier: License :: OSI Approved :: MIT License
Classifier: Programming Language :: Python
Classifier: Programming Language :: Python :: 3
Classifier: Programming Language :: Python :: 3.10
License-File: LICENSE
Dynamic: license-file
